MANIFEST.in
README.md
setup.py
django_themeswitch.egg-info/PKG-INFO
django_themeswitch.egg-info/SOURCES.txt
django_themeswitch.egg-info/dependency_links.txt
django_themeswitch.egg-info/top_level.txt
themeswitch/__init__.py
themeswitch/context_processors.py
themeswitch/models.py
themeswitch/settings.py
themeswitch/tests.py
themeswitch/urls.py
themeswitch/views.py
themeswitch/runtests/__init__.py
themeswitch/runtests/runcoverage.py
themeswitch/runtests/runtests.py
themeswitch/runtests/settings.py
themeswitch/runtests/urls.py
themeswitch/templatetags/__init__.py
themeswitch/templatetags/themeswitch_tags.py