Metadata-Version: 1.1
Name: django-themeswitch
Version: 0.3.1
Summary: a django app that allows for easy switch between themes
Home-page: https://github.com/nschlemm/django-themeswitch
Author: Nikolaus Schlemm
Author-email: capo@coder-nostra.org
License: BSD License
Platform: UNKNOWN
Classifier: Environment :: Web Environment
Classifier: Framework :: Django
Classifier: Intended Audience :: Developers
Classifier: License :: OSI Approved :: BSD License
Classifier: Operating System :: OS Independent
Classifier: Programming Language :: Python
Classifier: Programming Language :: Python :: 2.6
Classifier: Programming Language :: Python :: 2.7
Classifier: Topic :: Internet :: WWW/HTTP
Classifier: Topic :: Internet :: WWW/HTTP :: Dynamic Content
